docker_composer_v2/__init__.py
docker_composer_v2/_utils/__init__.py
docker_composer_v2/_utils/argument.py
docker_composer_v2/_utils/generate_class.py
docker_composer_v2/base.py
docker_composer_v2/py.typed
docker_composer_v2/runner/cmd/build.py
docker_composer_v2/runner/cmd/config.py
docker_composer_v2/runner/cmd/cp.py
docker_composer_v2/runner/cmd/create.py
docker_composer_v2/runner/cmd/down.py
docker_composer_v2/runner/cmd/events.py
docker_composer_v2/runner/cmd/exec.py
docker_composer_v2/runner/cmd/images.py
docker_composer_v2/runner/cmd/kill.py
docker_composer_v2/runner/cmd/logs.py
docker_composer_v2/runner/cmd/ls.py
docker_composer_v2/runner/cmd/pause.py
docker_composer_v2/runner/cmd/port.py
docker_composer_v2/runner/cmd/ps.py
docker_composer_v2/runner/cmd/pull.py
docker_composer_v2/runner/cmd/push.py
docker_composer_v2/runner/cmd/restart.py
docker_composer_v2/runner/cmd/rm.py
docker_composer_v2/runner/cmd/run.py
docker_composer_v2/runner/cmd/start.py
docker_composer_v2/runner/cmd/stop.py
docker_composer_v2/runner/cmd/top.py
docker_composer_v2/runner/cmd/unpause.py
docker_composer_v2/runner/cmd/up.py
docker_composer_v2/runner/cmd/version.py
docker_composer_v2/runner/root.py
docker_composer_v2-0.8.8.dist-info/LICENSE.txt
docker_composer_v2-0.8.8.dist-info/METADATA
docker_composer_v2-0.8.8.dist-info/WHEEL
docker_composer_v2-0.8.8.dist-info/RECORD
