Metadata-Version: 2.1
Name: docker-composer-v2
Version: 0.8.8
Summary: Use `docker compose` from within Python. This is a branch forked from https://github.com/schollm/docker-composer to support Docker Compose V2.
Home-page: https://github.com/jensenkairos/docker-composer-v2
License: Apache-2.0
Author: Micha
Author-email: schollm-git@gmx.com
Requires-Python: >=3.6,<4.0
Classifier: Development Status :: 4 - Beta
Classifier: Intended Audience :: Developers
Classifier: Intended Audience :: System Administrators
Classifier: License :: OSI Approved :: Apache Software License
Classifier: Operating System :: OS Independent
Classifier: Programming Language :: Python :: 3
Classifier: Programming Language :: Python :: 3.6
Classifier: Programming Language :: Python :: 3.7
Classifier: Programming Language :: Python :: 3.8
Classifier: Programming Language :: Python :: 3.9
Classifier: Programming Language :: Python :: 3.10
Classifier: Programming Language :: Python :: 3.11
Classifier: Programming Language :: Python :: 3
Classifier: Topic :: Software Development :: Build Tools
Classifier: Topic :: Software Development :: Libraries :: Application Frameworks
Requires-Dist: attrs (>=20.3.0,<21.0.0)
Requires-Dist: loguru (>=0.5.3,<0.6.0)
Project-URL: Repository, https://github.com/jensenkairos/docker-composer-v2
